enum_custom.py
enum34_custom-0.7.2.dist-info/DESCRIPTION.rst
enum34_custom-0.7.2.dist-info/METADATA
enum34_custom-0.7.2.dist-info/RECORD
enum34_custom-0.7.2.dist-info/WHEEL
enum34_custom-0.7.2.dist-info/metadata.json
enum34_custom-0.7.2.dist-info/top_level.txt
