Metadata-Version: 2.0
Name: enum34-custom
Version: 0.7.2
Summary: Custom Enum classes for enum in Python 3.4 or for enum34 for Python2.7
Home-page: https://github.com/kissgyorgy/enum34-custom
Author: Kiss György
Author-email: kissgyorgy@me.com
License: MIT
Keywords: enum
Platform: UNKNOWN
Classifier: Intended Audience :: Developers
Classifier: Programming Language :: Python
Classifier: License :: OSI Approved :: MIT License
Classifier: Programming Language :: Python :: 2
Classifier: Programming Language :: Python :: 2.7
Classifier: Programming Language :: Python :: 3
Classifier: Programming Language :: Python :: 3.4
Requires-Dist: enum34
Requires-Dist: six
